enjam-1.0.dist-info/METADATA
enjam-1.0.dist-info/WHEEL
enjam-1.0.dist-info/entry_points.txt
enjam-1.0.dist-info/licenses/LICENSE
enjam/__init__.py
enjam/aiotyper.py
enjam/main.py
enjam/numify.py
enjam-1.0.dist-info/RECORD
