Metadata-Version: 2.1
Name: enjam
Version: 1.0
Summary: batch convert videos
Keywords: ffmpeg,encoder,cli
Author-Email: Evstifeev Roman <someuniquename@gmail.com>
License: MIT
Classifier: Development Status :: 4 - Beta
Classifier: License :: OSI Approved :: MIT License
Classifier: Programming Language :: Python
Classifier: Programming Language :: Python :: 3
Classifier: Programming Language :: Python :: 3 :: Only
Classifier: Programming Language :: Python :: 3.11
Classifier: Programming Language :: Python :: 3.12
Requires-Python: >=3.11
Requires-Dist: typer>=0.12.4
Requires-Dist: django-environ>=0.9.0
Requires-Dist: rich>=13.4.2
Requires-Dist: shellingham>=1.5.0.post1
Requires-Dist: python-ffmpeg>=2.0.4
Requires-Dist: aiometer>=0.4.0
Requires-Dist: loguru>=0.7.0
Requires-Dist: humanize>=4.7.0
